Workbook
Name aporte: APP!$D$16
Name patrimonio: APP!$D$19
Name qtd_anos: APP!$D$17
Name rendimento_carteira: APP!$D$12
Name salario: APP!$D$11
Name sugestao_investimento: APP!$D$13
Name tx_mensal: APP!$D$18

Sheet APP
B10: CONFIGURAÇÕES
B11: Salário | D11: 5000
B12: Rendimento Carteira | D12: 0.01
B13: Sugestão de Investimento (30%) | D13: =D11*30% -> 1500
B15: INVESTIMENTO MENSAL
B16: Quanto investir por mês? | D16: 500
B17: Por quantos anos? | D17: 5
B18: Taxa de rendimentos mensais? | D18: 0.01079
B19: Patrimônio acumulado? | D19: =FV(tx_mensal,qtd_anos*12,aporte*-1) -> 41888.457
B20: Dividendos mensais? | D20: =patrimonio*rendimento_carteira -> 418.88457
B22: CENÁRIOS | D22: DIVIDENDO
A23: 2 | B23: Quanto em 2 anos? | C23: =FV($D$18,$A23*12,$D$16*-1) -> 13613.814 | D23: =C23*rendimento_carteira -> 136.13814
A24: 5 | B24: Quanto em 5 anos? | C24: =FV($D$18,$A24*12,$D$16*-1) -> 41888.457 | D24: =C24*rendimento_carteira -> 418.88457
A25: 10 | B25: Quanto em 10 anos? | C25: =FV($D$18,$A25*12,$D$16*-1) -> 121642.11 | D25: =C25*rendimento_carteira -> 1216.4211
A26: 20 | B26: Quanto em 20 anos? | C26: =FV($D$18,$A26*12,$D$16*-1) -> 562599.2 | D26: =C26*rendimento_carteira -> 5625.992
A27: 30 | B27: Quanto em 30 anos? | C27: =FV($D$18,$A27*12,$D$16*-1) -> 2161084.8 | D27: =C27*rendimento_carteira -> 21610.848
B30: PERFIL | C30: MODERADO
B31: VALOR A SER INVESTIDO POR MÊS | C31: =aporte -> 500
B33: TIPO DE FII | C33: Percentual Sugerido | D33: Valores
B34: PAPEL | C34: =VLOOKUP($C$30&"-"&B34,BASE!$A:$D,4,) -> 0.32 | D34: =C34*$C$31 -> 160
B35: TIJOLO | C35: =VLOOKUP($C$30&"-"&B35,BASE!$A:$D,4,) -> 0.35 | D35: =C35*$C$31 -> 175
B36: HIBRIDOS | C36: =VLOOKUP($C$30&"-"&B36,BASE!$A:$D,4,) -> 0.08 | D36: =C36*$C$31 -> 40
B37: FOFs | C37: =VLOOKUP($C$30&"-"&B37,BASE!$A:$D,4,) -> 0.05 | D37: =C37*$C$31 -> 25
B38: DESENVOLVIMENTO | C38: =VLOOKUP($C$30&"-"&B38,BASE!$A:$D,4,) -> 0.1 | D38: =C38*$C$31 -> 50
B39: HOTELARIAS | C39: =VLOOKUP($C$30&"-"&B39,BASE!$A:$D,4,) -> 0.1 | D39: =C39*$C$31 -> 50
D40: =SUM(D34:D39) -> 500

Sheet BASE
A3: CHAVE | B3: PERFIL | C3: TIPO DE FII | D3: %
A4: =B4&"-"&C4 -> CONSERVADOR-PAPEL | B4: CONSERVADOR | C4: PAPEL | D4: 0.3
A5: =B5&"-"&C5 -> CONSERVADOR-TIJOLO | B5: CONSERVADOR | C5: TIJOLO | D5: 0.5 | F5: MODERADO-TIJOLO | G5: =VLOOKUP(F5,A3:D21,4,) -> 0.35
A6: =B6&"-"&C6 -> CONSERVADOR-HIBRIDOS | B6: CONSERVADOR | C6: HIBRIDOS | D6: 0.1
A7: =B7&"-"&C7 -> CONSERVADOR-FOFs | B7: CONSERVADOR | C7: FOFs | D7: 0.1
A8: =B8&"-"&C8 -> CONSERVADOR-DESENVOLVIMENTO | B8: CONSERVADOR | C8: DESENVOLVIMENTO | D8: 0
A9: =B9&"-"&C9 -> CONSERVADOR-HOTELARIAS | B9: CONSERVADOR | C9: HOTELARIAS | D9: 0
A10: =B10&"-"&C10 -> MODERADO-PAPEL | B10: MODERADO | C10: PAPEL | D10: 0.32
A11: =B11&"-"&C11 -> MODERADO-TIJOLO | B11: MODERADO | C11: TIJOLO | D11: 0.35
A12: =B12&"-"&C12 -> MODERADO-HIBRIDOS | B12: MODERADO | C12: HIBRIDOS | D12: 0.08
A13: =B13&"-"&C13 -> MODERADO-FOFs | B13: MODERADO | C13: FOFs | D13: 0.05
A14: =B14&"-"&C14 -> MODERADO-DESENVOLVIMENTO | B14: MODERADO | C14: DESENVOLVIMENTO | D14: 0.1
A15: =B15&"-"&C15 -> MODERADO-HOTELARIAS | B15: MODERADO | C15: HOTELARIAS | D15: 0.1
A16: =B16&"-"&C16 -> AGRESSIVO-PAPEL | B16: AGRESSIVO | C16: PAPEL | D16: 0.5
A17: =B17&"-"&C17 -> AGRESSIVO-TIJOLO | B17: AGRESSIVO | C17: TIJOLO | D17: 0.1
... A21: =B21&"-"&C21 -> AGRESSIVO-HOTELARIAS | B21: AGRESSIVO | C21: HOTELARIAS | D21: 0.1
